kozmoserver_supervisor_explain/__init__.py
kozmoserver_supervisor_explain/common.py
kozmoserver_supervisor_explain/errors.py
kozmoserver_supervisor_explain/explainers/__init__.py
kozmoserver_supervisor_explain/explainers/black_box_runtime.py
kozmoserver_supervisor_explain/explainers/integrated_gradients.py
kozmoserver_supervisor_explain/explainers/sklearn_api_runtime.py
kozmoserver_supervisor_explain/explainers/white_box_runtime.py
kozmoserver_supervisor_explain/runtime.py
kozmoserver_supervisor_explain/supervisor_dependency_reference.py
kozmoserver_supervisor_explain/version.py
kozmoserver_supervisor_explain-0.1.0.dev1.dist-info/LICENSE
kozmoserver_supervisor_explain-0.1.0.dev1.dist-info/METADATA
kozmoserver_supervisor_explain-0.1.0.dev1.dist-info/WHEEL
kozmoserver_supervisor_explain-0.1.0.dev1.dist-info/RECORD
